{"0":{"tipo":"Audiencia","fecha":"2025-11-19","titulo":"Audiencia general del 19 de noviembre de 2025 Ciclo de catequesis - Jubileo 2025. Jesucristo, nuestra esperanza. IV. La Resurreci\u00f3n de Cristo y los desaf\u00edos del mundo actual 5. Espiritualidad pascual y ecolog\u00eda integral","url":"https:\/\/www.vatican.va\/content\/leo-xiv\/es\/audiences\/2025\/documents\/20251119-udienza-generale.html","texto":"LE\u00d3N XIV\nAUDIENCIA GENERAL\nPlaza de San Pedro Mi\u00e9rcoles, 19 de noviembre de 2025\n[ Multimedia ]\n___________________________________\nCiclo de catequesis - Jubileo 2025. Jesucristo, nuestra esperanza. IV. La Resurreci\u00f3n de Cristo y los desaf\u00edos del mundo actual 5.\u00a0Espiritualidad pascual y ecolog\u00eda integral.\nQueridos hermanos y hermanas, \u00a1buenos d\u00edas y bienvenidos!\nEstamos reflexionando, en este A\u00f1o jubilar dedicado a la esperanza, sobre la relaci\u00f3n entre la Resurrecci\u00f3n de Cristo y los desaf\u00edos del mundo actual, es decir nuestros desaf\u00edos. A veces, Jes\u00fas, el Viviente, tambi\u00e9n nos quiere preguntar: \u00ab\u00bfPor qu\u00e9 lloras? \u00bfA qui\u00e9n buscas?\u00bb. Los desaf\u00edos, de hecho, no se pueden afrontar solos y las l\u00e1grimas son un don de vida cuando purifican nuestros ojos y liberan nuestra mirada.\nEl evangelista Juan nos llama la atenci\u00f3n sobre un detalle que no encontramos en los otros Evangelios: llorando cerca de la tumba vac\u00eda, la Magdalena no reconoci\u00f3 enseguida a Jes\u00fas resucitado, sino que pens\u00f3 que era el custodio del jard\u00edn. De hecho, ya narrando la sepultura de Jes\u00fas, al anochecer del viernes santo, el texto era muy preciso: \u00abEn el lugar donde hab\u00eda sido crucificado hab\u00eda un huerto, y en el huerto un sepulcro nuevo, en el que nadie todav\u00eda hab\u00eda sido depositado. All\u00ed, pues, porque era el d\u00eda de la Preparaci\u00f3n de los jud\u00edos y el sepulcro estaba cerca, pusieron a Jes\u00fas\u00bb ( Jn 19, 41-42).\nTermina as\u00ed, en la paz del s\u00e1bado y en la belleza de un jard\u00edn, la dram\u00e1tica lucha entre tinieblas y luz desatada con la traici\u00f3n, el arresto, el abandono, la condena, la humillaci\u00f3n y el asesinato del Hijo que \u00abhabiendo amado a los suyos que estaban en el mundo, los am\u00f3 hasta el extremo\u00bb (Jn 13,1). Cultivar y custodiar el jard\u00edn es la tarea originaria (cfr Gen 2,15) que Jes\u00fas llev\u00f3 a su t\u00e9rmino. Su \u00faltima palabra en la cruz \u2013 \u00abest\u00e1 cumplido\u00bb (Jn 19,30) \u2013 invita a cada uno a reencontrar la misma tarea, su tarea. Por esto, \u00abinclinando la cabeza, entreg\u00f3 el esp\u00edritu\u00bb (v. 30).\nQueridos hermanos y hermanas, \u00a1Mar\u00eda Magdalena, entonces, no se equivoc\u00f3 del todo, creyendo que encontraba al cuidador de la huerta! De hecho, deb\u00eda volver a escuchar el propio nombre y comprender la propia tarea del Hombre nuevo, la que en otro texto de Juan dice: \u00abhago nuevas todas las cosas\u00bb ( Ap 21,5). El Papa Francisco , con la enc\u00edclica Laudato si\u2019 , nos indic\u00f3 la extrema necesidad de una mirada contemplativa: si no es cuidador del jard\u00edn, el ser humano se convierte en su devastador.\nLa esperanza cristiana, por lo tanto, responde a los desaf\u00edos que enfrenta toda la humanidad hoy deteni\u00e9ndose en el jard\u00edn donde se coloc\u00f3 el Crucificado como una semilla, para volver a brotar y dar mucho fruto.\nEl Para\u00edso no est\u00e1 perdido, sino que es encontrado. La muerte y resurrecci\u00f3n de Jes\u00fas, por lo tanto, son el fundamento de una espiritualidad de la ecolog\u00eda integral, fuera de la cual las palabras de la fe se quedan sin conexi\u00f3n con la realidad y las palabras de la ciencia se quedan fuera del coraz\u00f3n. \u00abLa cultura ecol\u00f3gica no se puede reducir a una serie de respuestas urgentes y parciales a los problemas que van apareciendo en torno a la degradaci\u00f3n del ambiente, al agotamiento de las reservas naturales y a la contaminaci\u00f3n. Deber\u00eda ser una mirada distinta, un pensamiento, una pol\u00edtica, un programa educativo, un estilo de vida y una espiritualidad que conformen una resistencia\u00bb ( Laudato si\u2019 , 111).\nPor esto, hablamos de una conversi\u00f3n ecol\u00f3gica, que los cristianos no pueden separar de ese cambio de direcci\u00f3n que les requiere seguir a Jes\u00fas. El hecho de que Mar\u00eda se volviera aquella ma\u00f1ana de Pascua es una se\u00f1al de esto: solo de conversi\u00f3n en conversi\u00f3n pasamos de este valle de l\u00e1grimas a la nueva Jerusal\u00e9n. Tal pasaje, que empieza en el coraz\u00f3n y es espiritual, modifica la historia, nos compromete p\u00fablicamente, activa solidaridad que desde ahora protegen personas y criaturas de las ansias de los lobos, en el nombre y fuerza del \u00c1ngel Pastor.\nAs\u00ed, los hijos y las hijas de la Iglesia pueden hoy encontrar millones de j\u00f3venes y de otros hombres y mujeres de buena voluntad que han escuchado el grito de los pobres y de la tierra dej\u00e1ndose tocar el coraz\u00f3n. Son muchas tambi\u00e9n las personas que desean, a trav\u00e9s de una relaci\u00f3n m\u00e1s directa con la creaci\u00f3n, una nueva armon\u00eda que los lleve m\u00e1s all\u00e1 de tantas laceraciones. Por otro lado, adem\u00e1s \u00abel cielo proclama la gloria de Dios, el firmamento pregona la obra de sus manos: el d\u00eda al d\u00eda le pasa el mensaje, la noche a la noche se lo susurra. Sin que hablen, sin que pronuncien, sin que resuene su voz, a toda la tierra alcanza su preg\u00f3n y hasta los l\u00edmites del orbe su lenguaje\u00bb ( Sal 18,1-5).\nEl Esp\u00edritu nos d\u00e9 la capacidad de escuchar la voz de quien no tiene voz. Veremos, entonces, lo que los ojos a\u00fan no ven: ese jard\u00edn, o Para\u00edso, al que solo nos acercamos acogiendo y cumpliendo cada uno su propia tarea.\n_________________\nSaludos\nSaludo cordialmente a los peregrinos de lengua espa\u00f1ola. Pidamos al Se\u00f1or el don de saber cultivar una espiritualidad capaz de hacer germinar ese grano de trigo que como semilla de esperanza ha sido depuesto en el sepulcro, Cristo muerto y resucitado por nuestra salvaci\u00f3n, de modo que el cielo y la tierra proclamen siempre la gloria de Dios y la obra de sus manos (cf. Sal 18,1-5). Que Dios los bendiga. Muchas gracias.\n__________________\nResumen le\u00eddo por el Santo Padre en espa\u00f1ol\nQueridos hermanos y hermanas:\nSeguimos reflexionando sobre la Resurrecci\u00f3n de Cristo y su relaci\u00f3n con los desaf\u00edos del mundo actual. Uno de estos desaf\u00edos es la necesidad de una mirada contemplativa y de una conversi\u00f3n que no reduzca el cuidado de la creaci\u00f3n a una serie de respuestas a determinadas cuestiones urgentes.\nEn el relato evang\u00e9lico de la ma\u00f1ana de Pascua, encontramos a Mar\u00eda Magdalena en el jard\u00edn del sepulcro que llora la ausencia de Jes\u00fas. Es una imagen que nos evoca tambi\u00e9n el dolor que sentimos al ver la creaci\u00f3n privada de su verdadero sentido, explotada y degradada. Pero Jes\u00fas va al encuentro de Mar\u00eda, que aunque al inicio lo ve como el simple cuidador de ese jard\u00edn del Ed\u00e9n (cf. Gn 2,5), despu\u00e9s llega a reconocerlo como el Maestro y el Se\u00f1or que hace nuevas todas las cosas. Esta conversi\u00f3n, que comienza en el coraz\u00f3n y es espiritual, cambia la historia, nos compromete y nos impulsa a trabajar por el Reino sabi\u00e9ndonos administradores de los bienes que Dios nos ha entregado.","filename":"2025-11-19_audiencia_audiencia_general_del_19_de_noviembre_de_2025_ciclo_de_catequesis_jubileo_2025_jesucristo_nuestra_es"},"1":{"tipo":"Discurso","fecha":"2025-11-17","titulo":"A los participantes en el \"Seminario de \u00c9tica en el Gerenciamiento de la Salud\"  (17 de noviembre de 2025)","url":"https:\/\/www.vatican.va\/content\/leo-xiv\/es\/speeches\/2025\/november\/documents\/20251117-seminario-etica.html","texto":"DISCURSO DEL SANTO PADRE LE\u00d3N XIV A LOS PARTICIPANTES EN EL \"SEMINARIO DE \u00c9TICA EN EL GERENCIAMIENTO DE LA SALUD\"\nSala Clementina Lunes, 17 de noviembre de 2025\n[ Multimedia ]\n__________________\n\nEn el nombre del Padre, del Hijo y del Esp\u00edritu Santo. La paz est\u00e9 con ustedes.\nMuchas gracias. Bienvenidos a todos. Saludo a Mons. Bochatey, Director de este Seminario de \u00c9tica en el Gerenciamiento de Salud, y a todos los participantes en dicho Seminario que han querido encontrarse, bajo los auspicios de la Pontificia Academia para la Vida , para dialogar sobre la \u00e9tica en salud, la inteligencia artificial y las innovaciones tecnol\u00f3gicas y digitales.\nCon todo, al acercarse a las tumbas de los ap\u00f3stoles Pedro y Pablo en el marco de este a\u00f1o de Jubileo , su encuentro no tiene s\u00f3lo un valor formativo, sino que se convierte en una peregrinaci\u00f3n, en la cual, la reflexi\u00f3n sobre el valor \u00e9tico de nuestras propuestas se convierte en una hermosa etapa del camino que como sociedad y como Iglesia estamos llamados a recorrer. Hoy la Iglesia los acoge como peregrinos de esperanza, considerando valiosos sus distintos enfoques, competencias y prop\u00f3sitos, para entablar un di\u00e1logo de vida y acci\u00f3n en la tarea com\u00fan del cuidado del enfermo.\nMuchos son los aspectos interesantes que se desgranan de los temas que van a afrontar, tal vez demasiados para abordarlos juntos en este breve saludo, sin embargo, me permito evidenciar un concepto que me parece los acomuna. Me refiero a la posibilidad de un sesgo, de la introducci\u00f3n de una condici\u00f3n, una premisa, una nota que falsea, tronca, excluye de forma fraudulenta la percepci\u00f3n que tenemos de la realidad de la sociedad y del enfermo concreto, creando una situaci\u00f3n de injusticia en la gesti\u00f3n de los recursos necesarios para la recta administraci\u00f3n de la salud.\nSi como individuos y como sociedad estamos llamados a defender activamente la inequ\u00edvoca dignidad de todo ser humano, en todas las etapas y facetas de su existencia, lamentablemente, ello no siempre es real. Instrumentos tan eficaces como la inteligencia artificial pueden ser manipulados, entrenados, orientados para que, por razones de oportunidad o inter\u00e9s, ya sean econ\u00f3micas, pol\u00edticas o de otra \u00edndole, se genere ese sesgo a veces imperceptible en la informaci\u00f3n, en la gesti\u00f3n y en la manera en la que nos presentamos o nos acercamos al otro.\nLas personas entrar\u00e1n as\u00ed en una perversa manipulaci\u00f3n que las clasificar\u00e1 en virtud de los tratamientos necesarios y su coste, la naturaleza de sus enfermedades, convirti\u00e9ndolas en objetos, en datos, en estad\u00edsticas. La manera de evitarlo pienso que est\u00e1 en cambiar nuestra mirada, en percibir el valor del bien con una visi\u00f3n amplia, de mirar, si me permiten, como mira Dios, para no quedarnos en el lucro inmediato, sino en lo que ser\u00e1 mejor para todos, sabiendo ser pacientes, generosos y solidarios, creando lazos y tendiendo puentes, para trabajar en red, para optimizar los recursos, para que todos puedan sentirse protagonistas y beneficiarios del trabajo com\u00fan.\nAl mismo tiempo, Dios nos ense\u00f1a que esa visi\u00f3n amplia nunca se debe desligar del trato humano, de la caricia, del reconocimiento de la persona concreta, en su fragilidad y en su dignidad. Es una visi\u00f3n profunda, una visi\u00f3n que llega al coraz\u00f3n del otro y ensancha el nuestro. Estas dos visiones ser\u00e1n el mejor ant\u00eddoto para que nuestras estructuras gestionales no pierdan de vista lo importante: el bien que estamos llamados a custodiar. Que el Se\u00f1or nos ayude a ser fieles en este servicio. Muchas gracias.","filename":"2025-11-17_discurso_a_los_participantes_en_el_seminario_de_etica_en_el_gerenciamiento_de_la_salud_17_de_noviembre_de_202"}}